django_xformula/__init__.py
django_xformula/__version__.py
django_xformula/apps/__init__.py
django_xformula/apps/django_xformula_config.py
django_xformula/db/__init__.py
django_xformula/db/lookups/__init__.py
django_xformula/db/lookups/pure.py
django_xformula/errors/__init__.py
django_xformula/errors/forbidden_attribute.py
django_xformula/errors/forbidden_call.py
django_xformula/evaluator/__init__.py
django_xformula/evaluator/bidirectional_operator.py
django_xformula/evaluator/query_evaluator.py
django_xformula/protocols/__init__.py
django_xformula/protocols/attribute_getter.py
django_xformula/protocols/caller.py
django_xformula/tests/__init__.py
django_xformula/tests/evaluator/__init__.py
django_xformula/tests/evaluator/query_evaluator_test_case.py
django_xformula-0.1.3.dist-info/LICENSE
django_xformula-0.1.3.dist-info/METADATA
django_xformula-0.1.3.dist-info/WHEEL
django_xformula-0.1.3.dist-info/RECORD
