Metadata-Version: 2.1
Name: django-xformula
Version: 0.1.3
Summary: Django query evaluator, is built on top of XFormula language front-end.
License: MIT
Author: Ertuğrul Keremoğlu
Author-email: ertugkeremoglu@gmail.com
Requires-Python: >=3.11,<4.0
Classifier: License :: OSI Approved :: MIT License
Classifier: Programming Language :: Python :: 3
Classifier: Programming Language :: Python :: 3.11
Requires-Dist: django
Requires-Dist: xformula (>=0.1.1,<0.2.0)
